seqret/__init__.py
seqret/app.py
seqret/callbacks.py
seqret/cli.py
seqret/filters.py
seqret/layouts.py
seqret/optimizer.py
seqret/assets/DNA_color.ico
seqret/assets/favicon.ico
seqret-1.0.0.dist-info/LICENSE
seqret-1.0.0.dist-info/METADATA
seqret-1.0.0.dist-info/WHEEL
seqret-1.0.0.dist-info/entry_points.txt
seqret-1.0.0.dist-info/top_level.txt
seqret-1.0.0.dist-info/RECORD
